clockit.py
clockit-0.2.4.dist-info/DESCRIPTION.rst
clockit-0.2.4.dist-info/METADATA
clockit-0.2.4.dist-info/RECORD
clockit-0.2.4.dist-info/WHEEL
clockit-0.2.4.dist-info/metadata.json
clockit-0.2.4.dist-info/top_level.txt
