Metadata-Version: 2.0
Name: clockit
Version: 0.2.4
Summary: Tool for timing the execution of Python functions
Home-page: https://github.com/rlucioni/clockit
Author: Renzo Lucioni
Author-email: renzo@lucioni.email
License: MIT
Keywords: clockit
Platform: UNKNOWN
Classifier: Programming Language :: Python
Classifier: Development Status :: 3 - Alpha
Classifier: License :: OSI Approved :: MIT License
Classifier: Topic :: Software Development :: Libraries :: Python Modules
